{"100":{"service_id":143705,"color":"🚉"},"101":{"service_id":143711,"color":"🚉"},"110":{"service_id":345965,"color":"🟥"},"120":{"service_id":345917,"color":"🟥"},"121":{"service_id":345923,"color":"🟥"},"125":{"service_id":315299,"color":"🟥"},"126":{"service_id":273497,"color":"🟥"},"130":{"service_id":316259,"color":"🟥"},"200":{"service_id":312281,"color":"⬜"},"201":{"service_id":312293,"color":"⬜"},"202":{"service_id":345515,"color":"⬜"},"203":{"service_id":345797,"color":"⬜"},"204":{"service_id":345977,"color":"⬜"},"205":{"service_id":309941,"color":"⬜"},"206":{"service_id":246557,"color":"⬜"},"207":{"service_id":246563,"color":"⬜"},"208":{"service_id":291575,"color":"⬜"},"221":{"service_id":295913,"color":"⬜"},"230":{"service_id":273659,"color":"⬜"},"232":{"service_id":345509,"color":"⬜"},"233":{"service_id":329333,"color":"⬜"},"234":{"service_id":290555,"color":"⬜"},"235":{"service_id":332093,"color":"⬜"},"236":{"service_id":241715,"color":"⬜"},"240":{"service_id":294329,"color":"⬜"},"241":{"service_id":290567,"color":"⬜"},"242":{"service_id":291425,"color":"⬜"},"250":{"service_id":345695,"color":"⬜"},"251":{"service_id":345677,"color":"⬜"},"252":{"service_id":254837,"color":"⬜"},"260":{"service_id":227681,"color":"⬜"},"261":{"service_id":227693,"color":"⬜"},"270":{"service_id":292601,"color":"⬜"},"271":{"service_id":292607,"color":"⬜"},"300":{"service_id":316283,"color":"🟩"},"301":{"service_id":316289,"color":"🟩"},"302":{"service_id":316295,"color":"🟩"},"303":{"service_id":316301,"color":"🟩"},"304":{"service_id":316307,"color":"🟩"},"305":{"service_id":346559,"color":"🟩"},"308":{"service_id":346091,"color":"🟩"},"309":{"service_id":316319,"color":"🟩"},"310":{"service_id":316325,"color":"🟩"},"311":{"service_id":295613,"color":"🟩"},"312":{"service_id":294173,"color":"🟩"},"313":{"service_id":316331,"color":"🟩"},"314":{"service_id":245003,"color":"🟩"},"315":{"service_id":346433,"color":"🟩"},"316":{"service_id":316343,"color":"🟩"},"317":{"service_id":255665,"color":"🟩"},"319":{"service_id":316349,"color":"🟩"},"320":{"service_id":316415,"color":"🟩"},"330":{"service_id":316403,"color":"🟩"},"331":{"service_id":316409,"color":"🟩"},"350":{"service_id":345971,"color":"🟩"},"352":{"service_id":346217,"color":"🟩"},"353":{"service_id":346223,"color":"🟩"},"354":{"service_id":346229,"color":"🟩"},"370":{"service_id":346145,"color":"🟩"},"371":{"service_id":291173,"color":"🟩"},"372":{"service_id":346463,"color":"🟩"},"373":{"service_id":310727,"color":"🟩"},"400":{"service_id":290194,"color":"🟨"},"401":{"service_id":346157,"color":"🟨"},"402":{"service_id":312232,"color":"🟨"},"420":{"service_id":312220,"color":"🟨"},"421":{"service_id":233651,"color":"🟨"},"422":{"service_id":187499,"color":"🟨"},"440":{"service_id":313984,"color":"🟨"},"441":{"service_id":314008,"color":"🟨"},"442":{"service_id":314014,"color":"🟨"},"443":{"service_id":290278,"color":"🟨"},"461":{"service_id":346151,"color":"🟨"},"462":{"service_id":314045,"color":"🟨"},"463":{"service_id":295067,"color":"🟨"},"464":{"service_id":290248,"color":"🟨"},"465":{"service_id":290254,"color":"🟨"},"466":{"service_id":253846,"color":"🟨"},"467":{"service_id":273875,"color":"🟨"},"468":{"service_id":346163,"color":"🟨"},"520":{"service_id":294575,"color":"🟧"},"521":{"service_id":294581,"color":"🟧"},"522":{"service_id":273155,"color":"🟧"},"523":{"service_id":254267,"color":"🟧"},"524":{"service_id":246149,"color":"🟧"},"525":{"service_id":241415,"color":"🟧"},"530":{"service_id":345749,"color":"🟧"},"531":{"service_id":241427,"color":"🟧"},"532":{"service_id":312269,"color":"🟧"},"533":{"service_id":314009,"color":"🟧"},"534":{"service_id":237437,"color":"🟧"},"535":{"service_id":243461,"color":"🟧"},"540":{"service_id":294641,"color":"🟧"},"541":{"service_id":294647,"color":"🟧"},"542":{"service_id":243473,"color":"🟧"},"543":{"service_id":243479,"color":"🟧"},"544":{"service_id":241475,"color":"🟧"},"545":{"service_id":241481,"color":"🟧"},"546":{"service_id":243485,"color":"🟧"},"547":{"service_id":254279,"color":"🟧"},"548":{"service_id":310139,"color":"🟧"},"549":{"service_id":243491,"color":"🟧"},"550":{"service_id":292385,"color":"🟧"},"551":{"service_id":292427,"color":"🟧"},"552":{"service_id":292457,"color":"🟧"},"553":{"service_id":346439,"color":"🟧"},"554":{"service_id":310145,"color":"🟧"},"555":{"service_id":292253,"color":"🟧"},"556":{"service_id":292469,"color":"🟧"},"557":{"service_id":243533,"color":"🟧"},"558":{"service_id":292475,"color":"🟧"},"559":{"service_id":310151,"color":"🟧"},"560":{"service_id":314207,"color":"🟧"},"561":{"service_id":292481,"color":"🟧"},"562":{"service_id":243545,"color":"🟧"},"563":{"service_id":243551,"color":"🟧"},"564":{"service_id":292487,"color":"🟧"},"570":{"service_id":312419,"color":"🟧"},"600":{"service_id":312527,"color":"🟦"},"601":{"service_id":312545,"color":"🟦"},"602":{"service_id":345743,"color":"🟦"},"603":{"service_id":345737,"color":"🟦"},"604":{"service_id":312569,"color":"🟦"},"605":{"service_id":345725,"color":"🟦"},"606":{"service_id":345719,"color":"🟦"},"607":{"service_id":345713,"color":"🟦"},"608":{"service_id":312593,"color":"🟦"},"609":{"service_id":346103,"color":"🟦"},"610":{"service_id":346289,"color":"🟦"},"611":{"service_id":346295,"color":"🟦"},"612":{"service_id":315863,"color":"🟦"},"613":{"service_id":346115,"color":"🟦"},"620":{"service_id":346781,"color":"🟦"},"625":{"service_id":233069,"color":"🟦"},"630":{"service_id":346571,"color":"🟦"},"640":{"service_id":346565,"color":"🟦"},"645":{"service_id":312623,"color":"🟦"},"650":{"service_id":346481,"color":"🟦"},"651":{"service_id":315845,"color":"🟦"},"653":{"service_id":315851,"color":"🟦"},"660":{"service_id":332993,"color":"🟦"},"661":{"service_id":332999,"color":"🟦"},"665":{"service_id":346301,"color":"🟦"},"670":{"service_id":293261,"color":"🟦"},"675":{"service_id":333011,"color":"🟦"},"676":{"service_id":333023,"color":"🟦"},"680":{"service_id":346235,"color":"🟦"},"697":{"service_id":228815,"color":"🟦"},"698":{"service_id":228821,"color":"🟦"},"700":{"service_id":268349,"color":"🟦"},"701":{"service_id":166733,"color":"🟦"},"704":{"service_id":316085,"color":"🟦"},"705":{"service_id":314597,"color":"🟦"},"707":{"service_id":316067,"color":"🟦"},"708":{"service_id":176483,"color":"🟦"},"709":{"service_id":238277,"color":"🟦"},"710":{"service_id":231761,"color":"🟦"},"711":{"service_id":268355,"color":"🟦"},"713":{"service_id":274163,"color":"🟦"},"714":{"service_id":227585,"color":"🟦"},"716":{"service_id":255965,"color":"🟦"},"720":{"service_id":314339,"color":"🟦"},"721":{"service_id":314021,"color":"🟦"},"722":{"service_id":283169,"color":"🟦"},"723":{"service_id":283175,"color":"🟦"},"724":{"service_id":315485,"color":"🟦"},"729":{"service_id":294191,"color":"🟦"},"730":{"service_id":232799,"color":"🟦"},"731":{"service_id":232805,"color":"🟦"},"732":{"service_id":330221,"color":"🟦"},"733":{"service_id":328589,"color":"🟦"},"734":{"service_id":315491,"color":"🟦"},"740":{"service_id":283193,"color":"🟦"},"744":{"service_id":331931,"color":"🟦"},"750":{"service_id":332795,"color":"🟦"},"751":{"service_id":332777,"color":"🟦"},"752":{"service_id":332789,"color":"🟦"},"753":{"service_id":293783,"color":"🟦"},"754":{"service_id":268463,"color":"🟦"},"760":{"service_id":314585,"color":"🟦"},"761":{"service_id":244025,"color":"🟦"},"762":{"service_id":293903,"color":"🟦"},"763":{"service_id":244031,"color":"🟦"},"764":{"service_id":314591,"color":"🟦"},"765":{"service_id":254099,"color":"🟦"},"766":{"service_id":237761,"color":"🟦"},"767":{"service_id":187139,"color":"🟦"},"770":{"service_id":236717,"color":"🟦"},"771":{"service_id":236723,"color":"🟦"},"772":{"service_id":314687,"color":"🟦"},"773":{"service_id":235517,"color":"🟦"},"774":{"service_id":236045,"color":"🟦"},"775":{"service_id":236051,"color":"🟦"},"779":{"service_id":254105,"color":"🟦"},"780":{"service_id":310643,"color":"🟦"},"781":{"service_id":310373,"color":"🟦"},"782":{"service_id":236963,"color":"🟦"},"783":{"service_id":293789,"color":"🟦"},"799":{"service_id":232793,"color":"🟦"},"801":{"service_id":314297,"color":"🟪"},"802":{"service_id":314303,"color":"🟪"},"803":{"service_id":314309,"color":"🟪"},"804":{"service_id":314321,"color":"🟪"},"810":{"service_id":315887,"color":"🟪"},"811":{"service_id":315899,"color":"🟪"},"812":{"service_id":309911,"color":"🟪"},"813":{"service_id":295277,"color":"🟪"},"815":{"service_id":236465,"color":"🟪"},"816":{"service_id":236477,"color":"🟪"},"817":{"service_id":293957,"color":"🟪"},"818":{"service_id":310739,"color":"🟪"},"820":{"service_id":295433,"color":"🟪"},"821":{"service_id":295469,"color":"🟪"},"823":{"service_id":295445,"color":"🟪"},"824":{"service_id":295457,"color":"🟪"},"830":{"service_id":292937,"color":"🟪"},"840":{"service_id":314201,"color":"🟪"},"850":{"service_id":295199,"color":"🟪"},"852":{"service_id":183419,"color":"🟪"},"854":{"service_id":284819,"color":"🟪"},"855":{"service_id":284825,"color":"🟪"},"856":{"service_id":332921,"color":"🟪"},"857":{"service_id":332975,"color":"🟪"},"860":{"service_id":273893,"color":"🟪"},"861":{"service_id":246101,"color":"🟪"},"863":{"service_id":295481,"color":"🟪"},"864":{"service_id":290951,"color":"🟪"},"865":{"service_id":346547,"color":"🟪"},"866":{"service_id":346553,"color":"🟪"},"867":{"service_id":295493,"color":"🟪"},"869":{"service_id":314483,"color":"🟪"},"870":{"service_id":332927,"color":"🟪"},"871":{"service_id":291653,"color":"🟪"},"872":{"service_id":291665,"color":"🟪"},"880":{"service_id":245069,"color":"🟪"},"881":{"service_id":245075,"color":"🟪"},"896":{"service_id":245081,"color":"🟪"},"897":{"service_id":292793,"color":"🟪"},"898":{"service_id":244091,"color":"🟪"},"900":{"service_id":345809,"color":"🟫"},"905":{"service_id":346241,"color":"🟫"},"910":{"service_id":346247,"color":"🟫"},"911":{"service_id":345983,"color":"🟫"},"912":{"service_id":346139,"color":"🟫"},"913":{"service_id":315749,"color":"🟫"},"914":{"service_id":345833,"color":"🟫"},"915":{"service_id":345839,"color":"🟫"},"920":{"service_id":315779,"color":"🟫"},"921":{"service_id":346451,"color":"🟫"},"925":{"service_id":315803,"color":"🟫"},"927":{"service_id":332135,"color":"🟫"},"928":{"service_id":315689,"color":"🟫"},"930":{"service_id":316055,"color":"🟫"},"931":{"service_id":315695,"color":"🟫"},"932":{"service_id":332141,"color":"🟫"},"935":{"service_id":346253,"color":"🟫"},"936":{"service_id":345995,"color":"🟫"},"937":{"service_id":346259,"color":"🟫"},"938":{"service_id":346001,"color":"🟫"},"940":{"service_id":346265,"color":"🟫"},"941":{"service_id":346007,"color":"🟫"},"942":{"service_id":346271,"color":"🟫"},"943":{"service_id":346031,"color":"🟫"},"945":{"service_id":346277,"color":"🟫"},"946":{"service_id":346283,"color":"🟫"},"947":{"service_id":346025,"color":"🟫"},"950":{"service_id":315551,"color":"🟫"},"951":{"service_id":315557,"color":"🟫"},"955":{"service_id":315563,"color":"🟫"},"960":{"service_id":315641,"color":"🟫"},"965":{"service_id":315659,"color":"🟫"},"970":{"service_id":332117,"color":"🟫"},"1208":{"service_id":224003,"color":"🔲"},"1873":{"service_id":245867,"color":"🔲"}}